Metadata-Version: 2.1
Name: lyygui
Version: 1.6
Summary: yyjdgui for lyy
Author: lyy
Author-email: 
License: MIT
License-File: LICENSE
